{
  "name": "profile_450db364-9b1b-41d8-b9fb-64ad06392dda.jpg",
  "bucket": "instagram-clone-bb72b.appspot.com",
  "contentType": "",
  "metageneration": 1,
  "generation": 1621916683975,
  "storageClass": "STANDARD",
  "etag": "someETag",
  "contentDisposition": "inline",
  "contentEncoding": "identity",
  "downloadTokens": [
    "deb6f857-d1c1-485f-990a-46b58fe7e5e9"
  ],
  "timeCreated": "2021-05-25T04:24:43.974Z",
  "updated": "2021-05-25T04:24:43.974Z",
  "size": 158267,
  "md5Hash": "I7Senki2e7KbHwEGEErFCA==",
  "crc32c": "508982871"
}